pythonkitchen/__init__.py
pythonkitchen/backup_jobs.py
pythonkitchen/cli.py
pythonkitchen/create_subset.py
pythonkitchen/custom_tree.py
pythonkitchen/deeplizard.py
pythonkitchen/deeplizard_downloader.py
pythonkitchen/deeplizard_lessons.csv
pythonkitchen/dliz_lesson_names.py
pythonkitchen/download_rebelway.py
pythonkitchen/extract_course.py
pythonkitchen/extract_lessons.py
pythonkitchen/generate_descriptions.py
pythonkitchen/ml_vfx.json
pythonkitchen/notion_blocks.py
pythonkitchen/prettyPrintJson.py
pythonkitchen/project_export.py
pythonkitchen/pypiAvailablity.py
pythonkitchen/report_broken_sources.py
pythonkitchen/resize_pdf.py
pythonkitchen/seq_renamer.py
pythonkitchen/split_payload.py
pythonkitchen/test_imgseg_api.py
pythonkitchen/test_predict.py
pythonkitchen/udemyCurriculum.py
pythonkitchen/yank_releases.py
pythonkitchen-0.1.6.dist-info/LICENSE
pythonkitchen-0.1.6.dist-info/METADATA
pythonkitchen-0.1.6.dist-info/WHEEL
pythonkitchen-0.1.6.dist-info/entry_points.txt
pythonkitchen-0.1.6.dist-info/RECORD
