Metadata-Version: 2.1
Name: pythonKitchen
Version: 0.1.6
Summary: Package description for pythonKitchen
License: MIT
Author: Suhail
Author-email: suhailece@gmail.com
Requires-Python: >=3.11.7,<4.0.0
Classifier: License :: OSI Approved :: MIT License
Classifier: Programming Language :: Python :: 3
Classifier: Programming Language :: Python :: 3.12
Classifier: Programming Language :: Python :: 3.13
Requires-Dist: beautifulsoup4 (>=4.13.4,<5.0.0)
Requires-Dist: browser-cookie3 (>=0.20.1,<0.21.0)
Requires-Dist: incept (>=0.1.78,<0.2.0)
Requires-Dist: ledu (>=0.1.3,<0.2.0)
Requires-Dist: lumiera (>=0.1.3,<0.2.0)
Requires-Dist: notion-client (>=2.3.0,<3.0.0)
Requires-Dist: oauthmanager (>=0.1.1,<0.2.0)
Requires-Dist: openai (>=1.76.0,<2.0.0)
Requires-Dist: openpyxl (>=3.1.5,<4.0.0)
Requires-Dist: pandas (>=2.2.3,<3.0.0)
Requires-Dist: parivaha (>=0.1.4,<0.2.0)
Requires-Dist: pillow (>=11.2.1,<12.0.0)
Requires-Dist: prefect[github] (>=3.1.5,<4.0.0)
Requires-Dist: pypdf (>=5.5.0,<6.0.0)
Requires-Dist: pytesseract (>=0.3.13,<0.4.0)
Requires-Dist: python-dotenv (>=1.1.0,<2.0.0)
Requires-Dist: requests (>=2.32.3,<3.0.0)
Requires-Dist: selenium (>=4.31.0,<5.0.0)
Requires-Dist: tabulate (>=0.9.0,<0.10.0)
Requires-Dist: webdriver-manager (>=4.0.2,<5.0.0)
